{
  "account": {
    "equity": 104910.85,
    "cash": -49207.86,
    "buying_power": 32444.67
  },
  "positions": [
    {
      "symbol": "ADBE",
      "qty": 31.0,
      "side": "long",
      "current_price": 244.0,
      "market_value": 7564.0,
      "avg_entry_price": 242.41,
      "cost_basis": 7514.71,
      "today_pl_pct": -0.145,
      "today_pl": -11.005,
      "total_pl_pct": 0.656,
      "total_pl": 49.29
    },
    {
      "symbol": "AMT",
      "qty": 55.0,
      "side": "long",
      "current_price": 174.08,
      "market_value": 9574.4,
      "avg_entry_price": 171.29,
      "cost_basis": 9421.0,
      "today_pl_pct": -1.17,
      "today_pl": -113.3,
      "total_pl_pct": 1.628,
      "total_pl": 153.4
    },
    {
      "symbol": "AVGO",
      "qty": 21.0,
      "side": "long",
      "current_price": 344.9626,
      "market_value": 7244.21,
      "avg_entry_price": 307.09,
      "cost_basis": 6448.83,
      "today_pl_pct": 9.71,
      "today_pl": 641.1846,
      "total_pl_pct": 12.334,
      "total_pl": 795.38
    },
    {
      "symbol": "BKNG",
      "qty": 75.0,
      "side": "long",
      "current_price": 178.06,
      "market_value": 13354.5,
      "avg_entry_price": 169.34,
      "cost_basis": 12700.41,
      "today_pl_pct": 1.061,
      "today_pl": 5.61,
      "total_pl_pct": 5.15,
      "total_pl": 654.09
    },
    {
      "symbol": "C",
      "qty": 94.0,
      "side": "long",
      "current_price": 119.5,
      "market_value": 11233.0,
      "avg_entry_price": 115.64,
      "cost_basis": 10870.16,
      "today_pl_pct": 1.823,
      "today_pl": 201.16,
      "total_pl_pct": 3.338,
      "total_pl": 362.84
    },
    {
      "symbol": "CRM",
      "qty": 37.0,
      "side": "long",
      "current_price": 186.35,
      "market_value": 6894.95,
      "avg_entry_price": 183.71,
      "cost_basis": 6797.37,
      "today_pl_pct": 0.713,
      "today_pl": 48.84,
      "total_pl_pct": 1.436,
      "total_pl": 97.58
    },
    {
      "symbol": "CRWD",
      "qty": 14.0,
      "side": "long",
      "current_price": 434.0,
      "market_value": 6076.0,
      "avg_entry_price": 394.11,
      "cost_basis": 5517.54,
      "today_pl_pct": 8.878,
      "today_pl": 495.46,
      "total_pl_pct": 10.122,
      "total_pl": 558.46
    },
    {
      "symbol": "DDOG",
      "qty": 115.0,
      "side": "long",
      "current_price": 119.71,
      "market_value": 13766.65,
      "avg_entry_price": 116.53,
      "cost_basis": 13400.41,
      "today_pl_pct": 2.7550000000000003,
      "today_pl": 369.15,
      "total_pl_pct": 2.733,
      "total_pl": 366.24
    },
    {
      "symbol": "DHR",
      "qty": 49.0,
      "side": "long",
      "current_price": 191.01,
      "market_value": 9359.49,
      "avg_entry_price": 189.34,
      "cost_basis": 9277.66,
      "today_pl_pct": -0.5780000000000001,
      "today_pl": -54.39,
      "total_pl_pct": 0.882,
      "total_pl": 81.83
    },
    {
      "symbol": "GE",
      "qty": 31.0,
      "side": "long",
      "current_price": 298.57,
      "market_value": 9255.67,
      "avg_entry_price": 286.45,
      "cost_basis": 8879.95,
      "today_pl_pct": 3.422,
      "today_pl": 306.28,
      "total_pl_pct": 4.231,
      "total_pl": 375.72
    },
    {
      "symbol": "NET",
      "qty": 66.0,
      "side": "long",
      "current_price": 222.25,
      "market_value": 14668.5,
      "avg_entry_price": 203.78,
      "cost_basis": 13449.48,
      "today_pl_pct": 4.944,
      "today_pl": 691.02,
      "total_pl_pct": 9.064,
      "total_pl": 1219.02
    },
    {
      "symbol": "SBUX",
      "qty": 105.0,
      "side": "long",
      "current_price": 96.53,
      "market_value": 10135.65,
      "avg_entry_price": 88.59,
      "cost_basis": 9302.4,
      "today_pl_pct": 1.846,
      "today_pl": 183.75,
      "total_pl_pct": 8.957,
      "total_pl": 833.25
    },
    {
      "symbol": "SNOW",
      "qty": 68.0,
      "side": "long",
      "current_price": 153.5,
      "market_value": 10438.0,
      "avg_entry_price": 154.65,
      "cost_basis": 10516.2,
      "today_pl_pct": 2.758,
      "today_pl": 280.16,
      "total_pl_pct": -0.744,
      "total_pl": -78.2
    },
    {
      "symbol": "TJX",
      "qty": 84.0,
      "side": "long",
      "current_price": 158.94,
      "market_value": 13350.96,
      "avg_entry_price": 162.29,
      "cost_basis": 13632.62,
      "today_pl_pct": -1.78,
      "today_pl": -241.92,
      "total_pl_pct": -2.066,
      "total_pl": -281.66
    },
    {
      "symbol": "ZS",
      "qty": 77.0,
      "side": "long",
      "current_price": 145.49,
      "market_value": 11202.73,
      "avg_entry_price": 137.21,
      "cost_basis": 10565.17,
      "today_pl_pct": 4.279,
      "today_pl": 459.69,
      "total_pl_pct": 6.035,
      "total_pl": 637.56
    }
  ],
  "portfolio_history": [
    {
      "date": "2026-03-10",
      "equity": null,
      "profit_loss": null
    },
    {
      "date": "2026-03-11",
      "equity": null,
      "profit_loss": null
    },
    {
      "date": "2026-03-12",
      "equity": null,
      "profit_loss": null
    },
    {
      "date": "2026-03-13",
      "equity": null,
      "profit_loss": null
    },
    {
      "date": "2026-03-14",
      "equity": null,
      "profit_loss": null
    },
    {
      "date": "2026-03-17",
      "equity": null,
      "profit_loss": null
    },
    {
      "date": "2026-03-18",
      "equity": null,
      "profit_loss": null
    },
    {
      "date": "2026-03-19",
      "equity": null,
      "profit_loss": null
    },
    {
      "date": "2026-03-20",
      "equity": null,
      "profit_loss": null
    },
    {
      "date": "2026-03-21",
      "equity": null,
      "profit_loss": null
    },
    {
      "date": "2026-03-24",
      "equity": null,
      "profit_loss": null
    },
    {
      "date": "2026-03-25",
      "equity": null,
      "profit_loss": null
    },
    {
      "date": "2026-03-26",
      "equity": null,
      "profit_loss": null
    },
    {
      "date": "2026-03-27",
      "equity": null,
      "profit_loss": null
    },
    {
      "date": "2026-03-28",
      "equity": null,
      "profit_loss": null
    },
    {
      "date": "2026-03-31",
      "equity": null,
      "profit_loss": null
    },
    {
      "date": "2026-04-01",
      "equity": 100000.0,
      "profit_loss": null
    },
    {
      "date": "2026-04-02",
      "equity": 112220.32,
      "profit_loss": -600.0
    },
    {
      "date": "2026-04-03",
      "equity": 113159.36,
      "profit_loss": 939.04
    },
    {
      "date": "2026-04-07",
      "equity": 101649.17,
      "profit_loss": -11510.19
    }
  ],
  "spy_history": [
    {
      "date": "2026-04-01",
      "equity": 100000.0
    },
    {
      "date": "2026-04-02",
      "equity": 100090.05
    },
    {
      "date": "2026-04-03",
      "equity": 100090.05
    },
    {
      "date": "2026-04-07",
      "equity": 100607.41
    }
  ],
  "rebalances": [
    {
      "date": "2026-04-02",
      "portfolio_value": 92090.53,
      "trades": [
        {
          "symbol": "AMT",
          "side": "buy",
          "quantity": 55.0,
          "price": 171.290909,
          "slippage_bps": 0
        },
        {
          "symbol": "GE",
          "side": "buy",
          "quantity": 31.0,
          "price": 286.45,
          "slippage_bps": 0
        },
        {
          "symbol": "AVGO",
          "side": "buy",
          "quantity": 21.0,
          "price": 307.087143,
          "slippage_bps": 0
        },
        {
          "symbol": "DHR",
          "side": "buy",
          "quantity": 49.0,
          "price": 189.34,
          "slippage_bps": 0
        },
        {
          "symbol": "DDOG",
          "side": "buy",
          "quantity": 115.0,
          "price": 116.525305,
          "slippage_bps": 0
        },
        {
          "symbol": "NET",
          "side": "buy",
          "quantity": 66.0,
          "price": 203.78,
          "slippage_bps": 0
        },
        {
          "symbol": "CRWD",
          "side": "sell",
          "quantity": 3.0,
          "price": 390.793333,
          "slippage_bps": 0
        },
        {
          "symbol": "ADBE",
          "side": "sell",
          "quantity": 7.0,
          "price": 241.0,
          "slippage_bps": 0
        },
        {
          "symbol": "SBUX",
          "side": "buy",
          "quantity": 105.0,
          "price": 88.594285,
          "slippage_bps": 0
        },
        {
          "symbol": "CRM",
          "side": "buy",
          "quantity": 37.0,
          "price": 183.712703,
          "slippage_bps": 0
        },
        {
          "symbol": "KLAC",
          "side": "sell",
          "quantity": 6.0,
          "price": 1451.0,
          "slippage_bps": 0
        },
        {
          "symbol": "MRVL",
          "side": "sell",
          "quantity": 34.0,
          "price": 102.76,
          "slippage_bps": 0
        },
        {
          "symbol": "IBM",
          "side": "sell",
          "quantity": 15.0,
          "price": 242.674667,
          "slippage_bps": 0
        },
        {
          "symbol": "MSFT",
          "side": "sell",
          "quantity": 21.0,
          "price": 366.5,
          "slippage_bps": 0
        },
        {
          "symbol": "TGT",
          "side": "sell",
          "quantity": 59.0,
          "price": 119.08678,
          "slippage_bps": 0
        },
        {
          "symbol": "TJX",
          "side": "buy",
          "quantity": 3.0,
          "price": 161.566667,
          "slippage_bps": 0
        }
      ]
    },
    {
      "date": "2026-04-01",
      "portfolio_value": 92090.53,
      "trades": [
        {
          "symbol": "ZS",
          "side": "buy",
          "quantity": 77.0,
          "price": 137.21,
          "slippage_bps": 0
        },
        {
          "symbol": "TJX",
          "side": "buy",
          "quantity": 81.0,
          "price": 162.32,
          "slippage_bps": 0
        },
        {
          "symbol": "TGT",
          "side": "buy",
          "quantity": 59.0,
          "price": 121.18,
          "slippage_bps": 0
        },
        {
          "symbol": "SNOW",
          "side": "buy",
          "quantity": 68.0,
          "price": 154.65,
          "slippage_bps": 0
        },
        {
          "symbol": "MSFT",
          "side": "buy",
          "quantity": 21.0,
          "price": 371.42,
          "slippage_bps": 0
        },
        {
          "symbol": "MRVL",
          "side": "buy",
          "quantity": 34.0,
          "price": 106.923824,
          "slippage_bps": 0
        },
        {
          "symbol": "KLAC",
          "side": "buy",
          "quantity": 6.0,
          "price": 1533.28,
          "slippage_bps": 0
        },
        {
          "symbol": "IBM",
          "side": "buy",
          "quantity": 15.0,
          "price": 244.81,
          "slippage_bps": 0
        },
        {
          "symbol": "CRWD",
          "side": "buy",
          "quantity": 17.0,
          "price": 394.11,
          "slippage_bps": 0
        },
        {
          "symbol": "C",
          "side": "buy",
          "quantity": 94.0,
          "price": 115.64,
          "slippage_bps": 0
        },
        {
          "symbol": "BKNG",
          "side": "buy",
          "quantity": 3.0,
          "price": 4233.47,
          "slippage_bps": 0
        },
        {
          "symbol": "ADBE",
          "side": "buy",
          "quantity": 38.0,
          "price": 242.41,
          "slippage_bps": 0
        }
      ]
    }
  ]
}